COPYING
MANIFEST.in
README
health_services_report.xml
health_services_view.xml
invoice.xml
setup.py
./__init__.py
./health_services.py
./health_services_report.xml
./health_services_view.xml
./invoice.py
./invoice.xml
./tryton.cfg
./data/health_service_sequences.xml
./doc/index.rst
./icons/folder-documents.svg
./locale/ar.po
./locale/de.po
./locale/el.po
./locale/es.po
./locale/fr.po
./locale/it_IT.po
./locale/ja_JP.po
./locale/lo.po
./locale/pt_BR.po
./locale/zh_CN.po
./report/health_services_report.odt
./security/access_rights.xml
./tests/__init__.py
./tests/test_health_services.py
./view/gnuhealth_health_service.xml
./view/gnuhealth_health_service_line.xml
./view/gnuhealth_health_service_line_tree.xml
./view/gnuhealth_health_service_tree.xml
./view/gnuhealth_prescription.xml
./view/health_service_invoice.xml
./view/invoice_form.xml
./view/invoice_tree.xml
./wizard/__init__.py
./wizard/create_health_service_invoice.xml
./wizard/wizard_health_services.py
data/health_service_sequences.xml
icons/README
icons/folder-documents.svg
locale/ar.po
locale/de.po
locale/el.po
locale/es.po
locale/fr.po
locale/it_IT.po
locale/ja_JP.po
locale/lo.po
locale/pt_BR.po
locale/zh_CN.po
report/health_services_report.odt
security/access_rights.xml
trytond_health_services.egg-info/PKG-INFO
trytond_health_services.egg-info/SOURCES.txt
trytond_health_services.egg-info/dependency_links.txt
trytond_health_services.egg-info/entry_points.txt
trytond_health_services.egg-info/not-zip-safe
trytond_health_services.egg-info/requires.txt
trytond_health_services.egg-info/top_level.txt
view/gnuhealth_health_service.xml
view/gnuhealth_health_service_line.xml
view/gnuhealth_health_service_line_tree.xml
view/gnuhealth_health_service_tree.xml
view/gnuhealth_prescription.xml
view/health_service_invoice.xml
view/invoice_form.xml
view/invoice_tree.xml
wizard/create_health_service_invoice.xml