Metadata-Version: 1.1
Name: trytond-health-services
Version: 3.2.9
Summary: GNU Health package to manage patient health related services
Home-page: http://health.gnu.org
Author: GNU Solidario
Author-email: health@gnusolidario.org
License: GPL-3
Download-URL: http://ftp.gnu.org/gnu/health/
Platform: UNKNOWN
Classifier: Development Status :: 5 - Production/Stable
Classifier: Environment :: Plugins
Classifier: Framework :: Tryton
Classifier: Intended Audience :: Developers
Classifier: Intended Audience :: Healthcare Industry
Classifier: License :: OSI Approved :: GNU General Public License (GPL)
Classifier: Natural Language :: English
Classifier: Natural Language :: Spanish
Classifier: Operating System :: OS Independent
Classifier: Programming Language :: Python :: 3
Classifier: Topic :: Scientific/Engineering :: Bio-Informatics
Classifier: Topic :: Scientific/Engineering :: Medical Science Apps.
